Workbook

Sheet Summary
A1: SanDisk (NASDAQ: SNDK) financial model
A2: FY2026E-FY2030E | USD | cutoff 2026-07-17 12:23 ET intraday | status: screen-grade
A4: Research status | B4: Screen-grade
A5: Information cutoff | B5: 2026-07-17 12:23 ET
A6: Current price | B6: =Assumptions!B4 -> 1470.63
A7: Market capitalization | B7: =Valuation!B6 -> 217785.24
A8: Enterprise value | B8: =Valuation!B9 -> 214050.24
A10: Base-case operating forecast
A11: Metric | B11: FY2026E | C11: FY2027E | D11: FY2028E | E11: FY2029E | F11: FY2030E
A12: Revenue | B12: =Forecast!B4 -> 19283 | C12: =Forecast!C4 -> 33205.326 | D12: =Forecast!D4 -> 31118.134 | E12: =Forecast!E4 -> 28006.321 | F12: =Forecast!F4 -> 27539.549
A13: Net income | B13: =Forecast!B12 -> 9462.5655 | C13: =Forecast!C12 -> 18973.65 | D13: =Forecast!D12 -> 13186.755 | E13: =Forecast!E12 -> 8659.3132 | F13: =Forecast!F12 -> 7393.6206
A14: Diluted EPS | B14: =Forecast!B14 -> 60.657471 | C14: =Forecast!C14 -> 123.20552 | D14: =Forecast!D14 -> 86.754967 | E14: =Forecast!E14 -> 57.346445 | F14: =Forecast!F14 -> 49.290804
A15: Gross margin | B15: =Forecast!B6 -> 0.68879324 | C15: =Forecast!C6 -> 0.74 | D15: =Forecast!D6 -> 0.58 | E15: =Forecast!E6 -> 0.46 | F15: =Forecast!F6 -> 0.42
A18: Scenario valuation
A19: Scenario | B19: Probability | C19: FY27 EPS | D19: FY29-30 avg EPS | E19: Fair value/share | F19: vs. price
A20: Bear | B20: =Valuation!B24 -> 0.3 | C20: =Valuation!C24 -> 52.066954 | D20: =Valuation!E24 -> 6.7750991 | E20: =Valuation!H24 -> 217.26485 | F20: =E20/$B$6-1 -> -0.8522641
A21: Base | B21: =Valuation!B25 -> 0.5 | C21: =Valuation!C25 -> 123.20552 | D21: =Valuation!E25 -> 53.318624 | E21: =Valuation!H25 -> 1054.6809 | F21: =E21/$B$6-1 -> -0.28283737
A22: Bull | B22: =Valuation!B26 -> 0.2 | C22: =Valuation!C26 -> 176.63993 | D22: =Valuation!E26 -> 206.77115 | E22: =Valuation!H26 -> 3322.312 | F22: =E22/$B$6-1 -> 1.259108
A23: Probability-weighted | E23: =Valuation!I27 -> 1256.9823 | F23: =Valuation!I28 -> -0.14527631
A26: Investor read-through
A27: 1. | B27: FY2026E is not reported actual: it combines FY2026 9M actuals with management's Q4 guidance midpoint.
A28: 2. | B28: Q3 growth was primarily price/mix driven; the model explicitly normalizes ASP and gross margin after FY2027.
A29: 3. | B29: The current price embeds either a low multiple on peak FY2027 earnings or a durable $41.5-$47.4bn normalized-revenue outcome.
A30: 4. | B30: RPO and NBM contracts improve visibility but do not eliminate delivery, repricing, customer and supply risks.
A31: 5. | B31: BiCS10 is stage-gated: no material base-case revenue before FY2028; HBF is excluded from base-case revenue.

Sheet Assumptions
A1: SanDisk assumptions register
A2: Blue cells are explicit inputs; model formulas reference this sheet.
A3: Assumption | B3: Value | C3: Unit | D3: Type | E3: Source / rationale | F3: Trigger or limitation
A4: Current price | B4: 1470.63 | C4: $/share | D4: Observed | E4: S18; Nasdaq 2026-07-17 12:23 ET | F4: Intraday, not close
A5: Basic shares outstanding | B5: 148.08976 | C5: mm | D5: Reported | E5: S6; as of 2026-04-24 | F5: May change after buybacks
A6: Cash | B6: 3735 | C6: $mm | D6: Reported | E6: S6; 2026-04-03 | F6: Predates Nanya investment
A7: Debt | B7: 0 | C7: $mm | D7: Reported | E7: S6; term loan repaid | F7: Flash Ventures commitments remain
A8: Nanya cash payment | B8: 972 | C8: $mm | D8: Reported | E8: S6 subsequent event | F8: Investment can also be treated as non-operating asset
A9: Last completed close | B9: 1411.08 | C9: $/share | D9: Observed | E9: S19; 2026-07-16 | F9: Included as reference only
A10: Q4 FY26 revenue midpoint | B10: 8000 | C10: $mm | D10: Guidance | E10: S5; range $7.75-$8.25bn | F10: Not reported actual
A11: Q4 FY26 GAAP gross margin midpoint | B11: 0.799 | C11: % | D11: Guidance | E11: S5; range 78.9%-80.9% | F11: Not reported actual
A12: Q4 FY26 GAAP opex midpoint | B12: 540.5 | C12: $mm | D12: Guidance | E12: S5; range $523-$558mm | F12: Not reported actual
A13: Q4 FY26 other income midpoint | B13: 22 | C13: $mm | D13: Guidance | E13: S5; range $12-$32mm | F13: Not reported actual
A14: FY26E full-year tax rate | B14: 0.143 | C14: % | D14: Model | E14: Calibrated from 9M actual; Q4 GAAP tax not guided | F14: Sensitivity required
A15: FY26E diluted shares | B15: 156 | C15: mm | D15: Model | E15: 9M 154mm; Q4 guide about 158mm | F15: Buyback execution unknown
... A20: FY26E D&A proxy | B20: 150 | C20: $mm | D20: Model | E20: 9M cash-flow disclosure plus Q4 estimate | F20: JV structure limits peer comparability
A21: Selected scenario | B21: Base | C21: text | D21: Model | E21: Central operating path | F21: Change only with explicit model revision
A22: Transition valuation weight | B22: 0.4 | C22: % | D22: Model | E22: Balances FY27 peak/transition earnings | F22: Not a market fact
A23: Normalized valuation weight | B23: 0.6 | C23: % | D23: Model | E23: Balances FY29-FY30 earnings | F23: Not a market fact
A24: FY26E non-GAAP EPS | B24: 62.82 | C24: $/share | D24: Derived | E24: 9M $31.32 + Q4 guide midpoint $31.50 | F24: Mixed actual and guidance
A25: Q4 FY26 diluted shares guide | B25: 158 | C25: mm | D25: Guidance | E25: S5; approximately 158mm | F25: Not reported actual
A28: Scenario valuation assumptions
A29: Metric | B29: Bear | C29: Base | D29: Bull | E29: Unit | F29: Rationale
A30: Transition P/E | B30: 8 | C30: 10 | D30: 14 | E30: x | F30: Peak-cycle earnings receive a lower multiple
A31: Normalized P/E | B31: 10 | C31: 16 | D31: 18 | E31: x | F31: Long-term contract validation and balance sheet support the range
A32: Excess cash / share | B32: 10 | C32: 50 | D32: 100 | E32: $/share | F32: Scenario treatment of cash, buyback and strategic investment

Sheet Historicals
A1: SanDisk historical financials
A2: $mm except per-share data; FY2026E is 9M actual plus Q4 guidance midpoint.
A3: Metric | B3: FY2023A | C3: FY2024A | D3: FY2025A | E3: FY2026 9M A | F3: FY2026E
A4: Revenue | B4: 6086 | C4: 6663 | D4: 7355 | E4: 11283 | F4: =E4+Assumptions!B10 -> 19283
A5: Gross profit | B5: 430 | C5: 1072 | D5: 2212 | E5: 6890 | F5: =E5+Assumptions!B10*Assumptions!B11 -> 13282
A6: Gross margin | B6: =B5/B4 -> 0.07065396 | C6: =C5/C4 -> 0.16088849 | D6: =D5/D4 -> 0.30074779 | E6: =E5/E4 -> 0.6106532 | F6: =F5/F4 -> 0.68879324
A7: Operating expenses | B7: 2465 | C7: 1540 | D7: 3589 | E7: 1538 | F7: =E7+Assumptions!B12 -> 2078.5
A8: Operating income | B8: -2035 | C8: -468 | D8: -1377 | E8: 5352 | F8: =F5-F7 -> 11203.5
A9: Interest and other, net | B9: 33 | C9: -35 | D9: -102 | E9: -184 | F9: =E9+Assumptions!B13 -> -162
A10: Pretax income | B10: -2002 | C10: -503 | D10: -1479 | E10: 5168 | F10: =F8+F9 -> 11041.5
A11: Income taxes | B11: 141 | C11: 169 | D11: 162 | E11: 638 | F11: =MAX(0,F10*Assumptions!B14) -> 1578.9345
A12: Net income | B12: -2143 | C12: -672 | D12: -1641 | E12: 4530 | F12: =F10-F11 -> 9462.5655
A13: Diluted shares | B13: 145 | C13: 145 | D13: 145 | E13: 154 | F13: =Assumptions!B15 -> 156
A14: Diluted EPS | B14: -14.78 | C14: -4.63 | D14: -11.32 | E14: 29.42 | F14: =F12/F13 -> 60.657471
A15: Operating cash flow | B15: -713 | C15: -309 | D15: 84 | E15: 4545
A16: PP&E purchases | B16: 219 | C16: 166 | D16: 204 | E16: 134
A18: Datacenter / Cloud revenue | B18: 500 | C18: 325 | D18: 960 | E18: 2176 | F18: =E18+Assumptions!B10*Assumptions!B17 -> 4576
A19: Edge / Client revenue | B19: 3637 | C19: 4069 | D19: 4127 | E19: 6728 | F19: =E19+Assumptions!B10*Assumptions!B18 -> 11368
A20: Consumer revenue | B20: 1949 | C20: 2269 | D20: 2268 | E20: 2379 | F20: =E20+Assumptions!B10*Assumptions!B19 -> 3339
A22: Perimeter note | B22: FY2023-FY2025 include carve-out allocations from Western Digital; pre-separation operating expenses are not fully comparable with standalone SanDisk.

Sheet Drivers
A1: SanDisk scenario drivers
A2: Q3 FY2026 ASP/GB and cost/GB are indexed to 100. All FY2027-FY2030 inputs are explicit scenarios, not guidance.
A3: Driver | B3: FY2027E | C3: FY2028E | D3: FY2029E | E3: FY2030E
A4: Bear
A5: Bit shipment growth | B5: 0.12 | C5: 0.16 | D5: 0.15 | E5: 0.14
A6: ASP / GB index | B6: 75 | C6: 45 | D6: 35 | E6: 32
A7: Cost / GB index | B7: 98 | C7: 89 | D7: 82 | E7: 76
A8: Gross margin | B8: 0.55 | C8: 0.3 | D8: 0.2 | E8: 0.28
A9: Operating expenses | B9: 2300 | C9: 2200 | D9: 2100 | E9: 2200
A10: Interest and other income | B10: 100 | C10: 100 | D10: 100 | E10: 100
A11: Tax rate | B11: 0.15 | C11: 0.15 | D11: 0.15 | E11: 0.16
A12: Diluted shares | B12: 158 | C12: 158 | D12: 157 | E12: 156
A13: Datacenter revenue share | B13: 0.3 | C13: 0.33 | D13: 0.36 | E13: 0.39
A14: Edge revenue share | B14: 0.53 | C14: 0.51 | D14: 0.49 | E14: 0.47
A15: Consumer revenue share | B15: 0.17 | C15: 0.16 | D15: 0.15 | E15: 0.14
A17: Base
A18: Bit shipment growth | B18: 0.23 | C18: 0.23 | D18: 0.2 | E18: 0.18
A19: ASP / GB index | B19: 105 | C19: 80 | D19: 60 | E19: 50
A20: Cost / GB index | B20: 90 | C20: 79 | D20: 70 | E20: 62
A21: Gross margin | B21: 0.74 | C21: 0.58 | D21: 0.46 | E21: 0.42
A22: Operating expenses | B22: 2450 | C22: 2650 | D22: 2850 | E22: 3050
A23: Interest and other income | B23: 200 | C23: 300 | D23: 400 | E23: 500
A24: Tax rate | B24: 0.15 | C24: 0.16 | D24: 0.17 | E24: 0.18
A25: Diluted shares | B25: 154 | C25: 152 | D25: 151 | E25: 150
A26: Datacenter revenue share | B26: 0.35 | C26: 0.44 | D26: 0.49 | E26: 0.53
A27: Edge revenue share | B27: 0.5 | C27: 0.43 | D27: 0.39 | E27: 0.36
A28: Consumer revenue share | B28: 0.15 | C28: 0.13 | D28: 0.12 | E28: 0.11
A30: Bull
A31: Bit shipment growth | B31: 0.33 | C31: 0.3 | D31: 0.26 | E31: 0.23
A32: ASP / GB index | B32: 125 | C32: 118 | D32: 105 | E32: 90
A33: Cost / GB index | B33: 86 | C33: 73 | D33: 64 | E33: 55
A34: Gross margin | B34: 0.8 | C34: 0.76 | D34: 0.68 | E34: 0.6
A35: Operating expenses | B35: 2600 | C35: 3000 | D35: 3400 | E35: 3800
A36: Interest and other income | B36: 200 | C36: 350 | D36: 500 | E36: 700
A37: Tax rate | B37: 0.15 | C37: 0.16 | D37: 0.17 | E37: 0.18
A38: Diluted shares | B38: 153 | C38: 148 | D38: 144 | E38: 140
A39: Datacenter revenue share | B39: 0.42 | C39: 0.55 | D39: 0.61 | E39: 0.65
A40: Edge revenue share | B40: 0.46 | C40: 0.35 | D40: 0.3 | E40: 0.27
A41: Consumer revenue share | B41: 0.12 | C41: 0.1 | D41: 0.09 | E41: 0.08
A43: Driver logic | B43: Revenue = prior-year revenue x (1 + bit growth) x (current ASP index / prior ASP index). Gross margin is separately calibrated to ASP, cost/GB, mix and utilization because absolute company cost/GB is not disclosed.

Sheet Scenarios
A1: SanDisk bear / base / bull scenarios
A2: $mm except per-share data. Probabilities are explicit judgment weights, not statistical frequencies.
A4: Scenario | B4: Probability
A5: Bear | B5: 0.3
A6: Base | B6: 0.5
A7: Bull | B7: 0.2
A8: Total | B8: =SUM(B5:B7) -> 1
A10: Revenue
A11: Scenario | B11: FY2027E | C11: FY2028E | D11: FY2029E | E11: FY2030E
A12: Bear | B12: =Forecast!$B$4*(1+Drivers!B5)*(Drivers!B6/Assumptions!$B$16) -> 21596.96 | C12: =B12*(1+Drivers!C5)*(Drivers!C6/Drivers!B6) -> 15031.484 | D12: =C12*(1+Drivers!D5)*(Drivers!D6/Drivers!C6) -> 13444.827 | E12: =D12*(1+Drivers!E5)*(Drivers!E6/Drivers!D6) -> 14013.352
A13: Base | B13: =Forecast!$B$4*(1+Drivers!B18)*(Drivers!B19/Assumptions!$B$16) -> 33205.326 | C13: =B13*(1+Drivers!C18)*(Drivers!C19/Drivers!B19) -> 31118.134 | D13: =C13*(1+Drivers!D18)*(Drivers!D19/Drivers!C19) -> 28006.321 | E13: =D13*(1+Drivers!E18)*(Drivers!E19/Drivers!D19) -> 27539.549
A14: Bull | B14: =Forecast!$B$4*(1+Drivers!B31)*(Drivers!B32/Assumptions!$B$16) -> 42743.983 | C14: =B14*(1+Drivers!C31)*(Drivers!C32/Drivers!B32) -> 52455.416 | D14: =C14*(1+Drivers!D31)*(Drivers!D32/Drivers!C32) -> 58812.302 | E14: =D14*(1+Drivers!E31)*(Drivers!E32/Drivers!D32) -> 62004.969
A16: Net income
A17: Scenario | B17: FY2027E | C17: FY2028E | D17: FY2029E | E17: FY2030E
A18: Bear | B18: =(B12*Drivers!B8-Drivers!B9+Drivers!B10)-MAX(0,(B12*Drivers!B8-Drivers!B9+Drivers!B10)*Drivers!B11) -> 8226.5788 | C18: =(C12*Drivers!C8-Drivers!C9+Drivers!C10)-MAX(0,(C12*Drivers!C8-Drivers!C9+Drivers!C10)*Drivers!C11) -> 2048.0285 | D18: =(D12*Drivers!D8-Drivers!D9+Drivers!D10)-MAX(0,(D12*Drivers!D8-Drivers!D9+Drivers!D10)*Drivers!D11) -> 585.62067 | E18: =(E12*Drivers!E8-Drivers!E9+Drivers!E10)-MAX(0,(E12*Drivers!E8-Drivers!E9+Drivers!E10)*Drivers!E11) -> 1531.9403
A19: Base | B19: =(B13*Drivers!B21-Drivers!B22+Drivers!B23)-MAX(0,(B13*Drivers!B21-Drivers!B22+Drivers!B23)*Drivers!B24) -> 18973.65 | C19: =(C13*Drivers!C21-Drivers!C22+Drivers!C23)-MAX(0,(C13*Drivers!C21-Drivers!C22+Drivers!C23)*Drivers!C24) -> 13186.755 | D19: =(D13*Drivers!D21-Drivers!D22+Drivers!D23)-MAX(0,(D13*Drivers!D21-Drivers!D22+Drivers!D23)*Drivers!D24) -> 8659.3132 | E19: =(E13*Drivers!E21-Drivers!E22+Drivers!E23)-MAX(0,(E13*Drivers!E21-Drivers!E22+Drivers!E23)*Drivers!E24) -> 7393.6206
A20: Bull | B20: =(B14*Drivers!B34-Drivers!B35+Drivers!B36)-MAX(0,(B14*Drivers!B34-Drivers!B35+Drivers!B36)*Drivers!B37) -> 27025.909 | C20: =(C14*Drivers!C34-Drivers!C35+Drivers!C36)-MAX(0,(C14*Drivers!C34-Drivers!C35+Drivers!C36)*Drivers!C37) -> 31261.538 | D20: =(D14*Drivers!D34-Drivers!D35+Drivers!D36)-MAX(0,(D14*Drivers!D34-Drivers!D35+Drivers!D36)*Drivers!D37) -> 30786.663 | E20: =(E14*Drivers!E34-Drivers!E35+Drivers!E36)-MAX(0,(E14*Drivers!E34-Drivers!E35+Drivers!E36)*Drivers!E37) -> 27964.445
A22: Diluted EPS
A23: Scenario | B23: FY2027E | C23: FY2028E | D23: FY2029E | E23: FY2030E
A24: Bear | B24: =B18/Drivers!B12 -> 52.066954 | C24: =C18/Drivers!C12 -> 12.962205 | D24: =D18/Drivers!D12 -> 3.730068 | E24: =E18/Drivers!E12 -> 9.8201302
A25: Base | B25: =B19/Drivers!B25 -> 123.20552 | C25: =C19/Drivers!C25 -> 86.754967 | D25: =D19/Drivers!D25 -> 57.346445 | E25: =E19/Drivers!E25 -> 49.290804
A26: Bull | B26: =B20/Drivers!B38 -> 176.63993 | C26: =C20/Drivers!C38 -> 211.22661 | D26: =D20/Drivers!D38 -> 213.79627 | E26: =E20/Drivers!E38 -> 199.74604
A28: Interpretation | B28: Bear is a supply-led price reset; Base assumes FY27 tightness followed by price normalization; Bull assumes durable AI/datacenter scarcity plus successful enterprise SSD execution.

Sheet Forecast
A1: SanDisk base-case annual forecast
A2: $mm except per-share data. FY2026E is mixed actual/guidance; FY2027E-FY2030E are explicit model estimates.
A3: Metric | B3: FY2026E | C3: FY2027E | D3: FY2028E | E3: FY2029E | F3: FY2030E
A4: Revenue | B4: =Historicals!F4 -> 19283 | C4: =B4*(1+Drivers!B18)*(Drivers!B19/Assumptions!B16) -> 33205.326 | D4: =C4*(1+Drivers!C18)*(Drivers!C19/Drivers!B19) -> 31118.134 | E4: =D4*(1+Drivers!D18)*(Drivers!D19/Drivers!C19) -> 28006.321 | F4: =E4*(1+Drivers!E18)*(Drivers!E19/Drivers!D19) -> 27539.549
A5: Gross profit | B5: =Historicals!F5 -> 13282 | C5: =C4*C6 -> 24571.941 | D5: =D4*D6 -> 18048.518 | E5: =E4*E6 -> 12882.908 | F5: =F4*F6 -> 11566.61
A6: Gross margin | B6: =B5/B4 -> 0.68879324 | C6: =Drivers!B21 -> 0.74 | D6: =Drivers!C21 -> 0.58 | E6: =Drivers!D21 -> 0.46 | F6: =Drivers!E21 -> 0.42
A7: Operating expenses | B7: =Historicals!F7 -> 2078.5 | C7: =Drivers!B22 -> 2450 | D7: =Drivers!C22 -> 2650 | E7: =Drivers!D22 -> 2850 | F7: =Drivers!E22 -> 3050
A8: Operating income | B8: =B5-B7 -> 11203.5 | C8: =C5-C7 -> 22121.941 | D8: =D5-D7 -> 15398.518 | E8: =E5-E7 -> 10032.908 | F8: =F5-F7 -> 8516.6104
A9: Interest and other income | B9: =Historicals!F9 -> -162 | C9: =Drivers!B23 -> 200 | D9: =Drivers!C23 -> 300 | E9: =Drivers!D23 -> 400 | F9: =Drivers!E23 -> 500
A10: Pretax income | B10: =B8+B9 -> 11041.5 | C10: =C8+C9 -> 22321.941 | D10: =D8+D9 -> 15698.518 | E10: =E8+E9 -> 10432.908 | F10: =F8+F9 -> 9016.6104
A11: Income taxes | B11: =Historicals!F11 -> 1578.9345 | C11: =MAX(0,C10*Drivers!B24) -> 3348.2912 | D11: =MAX(0,D10*Drivers!C24) -> 2511.7628 | E11: =MAX(0,E10*Drivers!D24) -> 1773.5943 | F11: =MAX(0,F10*Drivers!E24) -> 1622.9899
A12: Net income | B12: =B10-B11 -> 9462.5655 | C12: =C10-C11 -> 18973.65 | D12: =D10-D11 -> 13186.755 | E12: =E10-E11 -> 8659.3132 | F12: =F10-F11 -> 7393.6206
A13: Diluted shares | B13: =Historicals!F13 -> 156 | C13: =Drivers!B25 -> 154 | D13: =Drivers!C25 -> 152 | E13: =Drivers!D25 -> 151 | F13: =Drivers!E25 -> 150
A14: Diluted EPS | B14: =B12/B13 -> 60.657471 | C14: =C12/C13 -> 123.20552 | D14: =D12/D13 -> 86.754967 | E14: =E12/E13 -> 57.346445 | F14: =F12/F13 -> 49.290804
A15: EBITDA proxy | B15: =B8+Assumptions!B20 -> 11353.5 | C15: =C8+Assumptions!$B$20 -> 22271.941 | D15: =D8+Assumptions!$B$20 -> 15548.518 | E15: =E8+Assumptions!$B$20 -> 10182.908 | F15: =F8+Assumptions!$B$20 -> 8666.6104
A16: Datacenter revenue | B16: =Historicals!F18 -> 4576 | C16: =C4*Drivers!B26 -> 11621.864 | D16: =D4*Drivers!C26 -> 13691.979 | E16: =E4*Drivers!D26 -> 13723.097 | F16: =F4*Drivers!E26 -> 14595.961
A17: Edge revenue | B17: =Historicals!F19 -> 11368 | C17: =C4*Drivers!B27 -> 16602.663 | D17: =D4*Drivers!C27 -> 13380.798 | E17: =E4*Drivers!D27 -> 10922.465 | F17: =F4*Drivers!E27 -> 9914.2375
A18: Consumer revenue | B18: =Historicals!F20 -> 3339 | C18: =C4*Drivers!B28 -> 4980.7989 | D18: =D4*Drivers!C28 -> 4045.3574 | E18: =E4*Drivers!D28 -> 3360.7585 | F18: =F4*Drivers!E28 -> 3029.3504
A21: Caveat | B21: The gross-margin path is an explicit cycle/contract/mix calibration. Q3/Q4 FY2026 scarcity margins are not treated as a permanent cost structure.

Sheet Quarterly
A1: FY2027 quarterly scenario schedule
A2: $mm except per-share data. Quarterly shapes are model assumptions and reconcile to each FY2027 scenario.
A3: Metric | B3: Q1 FY27E | C3: Q2 FY27E | D3: Q3 FY27E | E3: Q4 FY27E
A4: Bear
A5: Revenue | B5: 6500 | C5: 5700 | D5: 5000 | E5: =Scenarios!B12-SUM(B5:D5) -> 4396.96
A6: Gross margin | B6: 0.68 | C6: 0.58 | D6: 0.48 | E6: 0.42
A7: Gross profit | B7: =B5*B6 -> 4420 | C7: =C5*C6 -> 3306 | D7: =D5*D6 -> 2400 | E7: =E5*E6 -> 1846.7232
A8: Operating expenses | B8: =Drivers!B9/4 -> 575 | C8: =Drivers!B9/4 -> 575 | D8: =Drivers!B9/4 -> 575 | E8: =Drivers!B9/4 -> 575
A9: Operating income | B9: =B7-B8 -> 3845 | C9: =C7-C8 -> 2731 | D9: =D7-D8 -> 1825 | E9: =E7-E8 -> 1271.7232
A10: Other income | B10: =Drivers!B10/4 -> 25 | C10: =Drivers!B10/4 -> 25 | D10: =Drivers!B10/4 -> 25 | E10: =Drivers!B10/4 -> 25
A11: Pretax income | B11: =B9+B10 -> 3870 | C11: =C9+C10 -> 2756 | D11: =D9+D10 -> 1850 | E11: =E9+E10 -> 1296.7232
A12: Income taxes | B12: =MAX(0,B11*Drivers!B11) -> 580.5 | C12: =MAX(0,C11*Drivers!B11) -> 413.4 | D12: =MAX(0,D11*Drivers!B11) -> 277.5 | E12: =MAX(0,E11*Drivers!B11) -> 194.50848
A13: Net income | B13: =B11-B12 -> 3289.5 | C13: =C11-C12 -> 2342.6 | D13: =D11-D12 -> 1572.5 | E13: =E11-E12 -> 1102.2147
A14: Diluted EPS | B14: =B13/Drivers!B12 -> 20.81962 | C14: =C13/Drivers!B12 -> 14.826582 | D14: =D13/Drivers!B12 -> 9.9525316 | E14: =E13/Drivers!B12 -> 6.9760425
A16: Base
A17: Revenue | B17: 8600 | C17: 8800 | D17: 8300 | E17: =Scenarios!B13-SUM(B17:D17) -> 7505.326
A18: Gross margin | B18: 0.8 | C18: 0.79 | D18: 0.72 | E18: 0.65
A19: Gross profit | B19: =B17*B18 -> 6880 | C19: =C17*C18 -> 6952 | D19: =D17*D18 -> 5976 | E19: =E17*E18 -> 4878.4619
A20: Operating expenses | B20: =Drivers!B22/4 -> 612.5 | C20: =Drivers!B22/4 -> 612.5 | D20: =Drivers!B22/4 -> 612.5 | E20: =Drivers!B22/4 -> 612.5
A21: Operating income | B21: =B19-B20 -> 6267.5 | C21: =C19-C20 -> 6339.5 | D21: =D19-D20 -> 5363.5 | E21: =E19-E20 -> 4265.9619
A22: Other income | B22: =Drivers!B23/4 -> 50 | C22: =Drivers!B23/4 -> 50 | D22: =Drivers!B23/4 -> 50 | E22: =Drivers!B23/4 -> 50
A23: Pretax income | B23: =B21+B22 -> 6317.5 | C23: =C21+C22 -> 6389.5 | D23: =D21+D22 -> 5413.5 | E23: =E21+E22 -> 4315.9619
A24: Income taxes | B24: =MAX(0,B23*Drivers!B24) -> 947.625 | C24: =MAX(0,C23*Drivers!B24) -> 958.425 | D24: =MAX(0,D23*Drivers!B24) -> 812.025 | E24: =MAX(0,E23*Drivers!B24) -> 647.39428
A25: Net income | B25: =B23-B24 -> 5369.875 | C25: =C23-C24 -> 5431.075 | D25: =D23-D24 -> 4601.475 | E25: =E23-E24 -> 3668.5676
A26: Diluted EPS | B26: =B25/Drivers!B25 -> 34.869318 | C26: =C25/Drivers!B25 -> 35.266721 | D26: =D25/Drivers!B25 -> 29.879708 | E26: =E25/Drivers!B25 -> 23.821868
A28: Bull
A29: Revenue | B29: 9500 | C29: 10200 | D29: 11000 | E29: =Scenarios!B14-SUM(B29:D29) -> 12043.983
A30: Gross margin | B30: 0.82 | C30: 0.82 | D30: 0.81 | E30: 0.8
A31: Gross profit | B31: =B29*B30 -> 7790 | C31: =C29*C30 -> 8364 | D31: =D29*D30 -> 8910 | E31: =E29*E30 -> 9635.1867
A32: Operating expenses | B32: =Drivers!B35/4 -> 650 | C32: =Drivers!B35/4 -> 650 | D32: =Drivers!B35/4 -> 650 | E32: =Drivers!B35/4 -> 650
A33: Operating income | B33: =B31-B32 -> 7140 | C33: =C31-C32 -> 7714 | D33: =D31-D32 -> 8260 | E33: =E31-E32 -> 8985.1867
A34: Other income | B34: =Drivers!B36/4 -> 50 | C34: =Drivers!B36/4 -> 50 | D34: =Drivers!B36/4 -> 50 | E34: =Drivers!B36/4 -> 50
A35: Pretax income | B35: =B33+B34 -> 7190 | C35: =C33+C34 -> 7764 | D35: =D33+D34 -> 8310 | E35: =E33+E34 -> 9035.1867
A36: Income taxes | B36: =MAX(0,B35*Drivers!B37) -> 1078.5 | C36: =MAX(0,C35*Drivers!B37) -> 1164.6 | D36: =MAX(0,D35*Drivers!B37) -> 1246.5 | E36: =MAX(0,E35*Drivers!B37) -> 1355.278
A37: Net income | B37: =B35-B36 -> 6111.5 | C37: =C35-C36 -> 6599.4 | D37: =D35-D36 -> 7063.5 | E37: =E35-E36 -> 7679.9087
A38: Diluted EPS | B38: =B37/Drivers!B38 -> 39.944444 | C38: =C37/Drivers!B38 -> 43.133333 | D38: =D37/Drivers!B38 -> 46.166667 | E38: =E37/Drivers!B38 -> 50.195481

Sheet Valuation
A1: SanDisk current and normalized valuation
A2: $mm except per-share data. Current price is 2026-07-17 12:23 ET intraday, not a close.
A3: Metric | B3: Value | C3: Unit | D3: Definition
A4: Current price | B4: =Assumptions!B4 -> 1470.63 | C4: $/share | D4: Nasdaq intraday
A5: Basic shares outstanding | B5: =Assumptions!B5 -> 148.08976 | C5: mm | D5: SEC actual shares
A6: Market capitalization | B6: =B4*B5 -> 217785.24 | C6: $mm | D6: Price x basic shares
A7: Cash | B7: =Assumptions!B6 -> 3735 | C7: $mm | D7: Latest reported cash
A8: Debt | B8: =Assumptions!B7 -> 0 | C8: $mm | D8: Latest reported debt
A9: Enterprise value | B9: =B6+B8-B7 -> 214050.24 | C9: $mm | D9: Market cap + debt - cash
A10: Pro forma EV after Nanya cash payment | B10: =B9+Assumptions!B8 -> 215022.24 | C10: $mm | D10: Conservative cash-only treatment
A11: FY2026E revenue | B11: =Forecast!B4 -> 19283 | C11: $mm | D11: 9M actual + Q4 guide midpoint
A12: FY2026E GAAP net income | B12: =Forecast!B12 -> 9462.5655 | C12: $mm | D12: Model estimate
A13: FY2026E GAAP diluted EPS | B13: =Forecast!B14 -> 60.657471 | C13: $/share | D13: Model estimate
A14: FY2026E non-GAAP diluted EPS | B14: =Assumptions!B24 -> 62.82 | C14: $/share | D14: 9M actual + Q4 guide midpoint
A15: FY2026E EBITDA proxy | B15: =Forecast!B15 -> 11353.5 | C15: $mm | D15: Operating income + D&A proxy
A16: Current P/E on GAAP FY2026E | B16: =B4/B13 -> 24.244829 | C16: x | D16: Price / model EPS
A17: Current P/E on non-GAAP FY2026E | B17: =B4/B14 -> 23.41022 | C17: x | D17: Price / mixed actual-guide EPS
A18: EV / sales | B18: =B9/B11 -> 11.100464 | C18: x | D18: EV / FY2026E revenue
A19: EV / EBITDA proxy | B19: =B9/B15 -> 18.853238 | C19: x | D19: JV accounting limits peer comparison
A22: Scenario fair value
A23: Scenario | B23: Probability | C23: FY27 EPS | D23: Transition P/E | E23: FY29-30 avg EPS | F23: Normalized P/E | G23: Excess cash/share | H23: Fair value/share | I23: Probability-weighted
A24: Bear | B24: =Scenarios!B5 -> 0.3 | C24: =Scenarios!B24 -> 52.066954 | D24: =Assumptions!B30 -> 8 | E24: =AVERAGE(Scenarios!D24:E24) -> 6.7750991 | F24: =Assumptions!B31 -> 10 | G24: =Assumptions!B32 -> 10 | H24: =C24*D24*Assumptions!$B$22+E24*F24*Assumptions!$B$23+G24 -> 217.26485 | I24: =B24*H24 -> 65.179455
A25: Base | B25: =Scenarios!B6 -> 0.5 | C25: =Scenarios!B25 -> 123.20552 | D25: =Assumptions!C30 -> 10 | E25: =AVERAGE(Scenarios!D25:E25) -> 53.318624 | F25: =Assumptions!C31 -> 16 | G25: =Assumptions!C32 -> 50 | H25: =C25*D25*Assumptions!$B$22+E25*F25*Assumptions!$B$23+G25 -> 1054.6809 | I25: =B25*H25 -> 527.34044
A26: Bull | B26: =Scenarios!B7 -> 0.2 | C26: =Scenarios!B26 -> 176.63993 | D26: =Assumptions!D30 -> 14 | E26: =AVERAGE(Scenarios!D26:E26) -> 206.77115 | F26: =Assumptions!D31 -> 18 | G26: =Assumptions!D32 -> 100 | H26: =C26*D26*Assumptions!$B$22+E26*F26*Assumptions!$B$23+G26 -> 3322.312 | I26: =B26*H26 -> 664.46241
A27: Probability-weighted fair value | I27: =SUM(I24:I26) -> 1256.9823
A28: Upside / (downside) to intraday price | I28: =I27/B4-1 -> -0.14527631
A31: Current-price reverse valuation
A32: Normalized P/E | B32: Implied EPS | C32: Implied net income | D32: Revenue @30% NM | E32: Revenue @35% NM | F32: Revenue @40% NM
A33: 12 | B33: =$B$4/A33 -> 122.5525 | C33: =B33*Assumptions!$B$25 -> 19363.295 | D33: =C33/30% -> 64544.317 | E33: =C33/35% -> 55323.7 | F33: =C33/40% -> 48408.238
A34: 14 | B34: =$B$4/A34 -> 105.045 | C34: =B34*Assumptions!$B$25 -> 16597.11 | D34: =C34/30% -> 55323.7 | E34: =C34/35% -> 47420.314 | F34: =C34/40% -> 41492.775
A35: 16 | B35: =$B$4/A35 -> 91.914375 | C35: =B35*Assumptions!$B$25 -> 14522.471 | D35: =C35/30% -> 48408.238 | E35: =C35/35% -> 41492.775 | F35: =C35/40% -> 36306.178
A37: Interpretation | B37: At 14x and 35%-40% normalized net margin, the current price implies sustainable revenue of roughly $41.5-$47.4bn, more than 2x FY2026E guidance-midpoint revenue.

Sheet Sources
A1: Source manifest
A2: Evidence hierarchy: E0 filing/official observed data; E1 issuer primary; E3 reputable third-party estimate. Retrieval cutoff 2026-07-17 12:23 ET.
A3: Source ID | B3: Publisher | C3: Title | D3: Published | E3: Tier | F3: Metric / use | G3: URL | H3: Limitations
A4: S001 | B4: SanDisk Corporation | C4: Form 10-K FY2025 | D4: 2025-08-21 | E4: E0 | F4: GAAP income statement | G4: https://www.sec.gov/Archives/edgar/data/2023554/000202355425000034/sndk-20250627.htm | H4: Carve-out period before separation; allocated Western Digital costs may not equal standalone economics
A5: S002 | B5: SanDisk Corporation | C5: Form 10-K FY2025 | D5: 2025-08-21 | E5: E0 | F5: GAAP income statement | G5: https://www.sec.gov/Archives/edgar/data/2023554/000202355425000034/sndk-20250627.htm | H5: Carve-out period before separation; allocated Western Digital costs may not equal standalone economics
A6: S003 | B6: SanDisk Corporation | C6: Form 10-K FY2025 | D6: 2025-08-21 | E6: E0 | F6: GAAP income statement | G6: https://www.sec.gov/Archives/edgar/data/2023554/000202355425000034/sndk-20250627.htm | H6: Includes pre- and post-separation months and large noncash goodwill impairment
A7: S004 | B7: SanDisk Corporation | C7: Form 10-K FY2025 | D7: 2025-08-21 | E7: E0 | F7: Revenue by end market | G7: https://www.sec.gov/Archives/edgar/data/2023554/000202355425000034/sndk-20250627.htm | H7: Cloud renamed Datacenter and Client renamed Edge in FY2026; labels normalized only in the model
A8: S005 | B8: SanDisk Corporation | C8: Form 10-K FY2025 | D8: 2025-08-21 | E8: E0 | F8: Separation and fiscal-calendar perimeter | G8: https://www.sec.gov/Archives/edgar/data/2023554/000202355425000034/sndk-20250627.htm | H8: Historical comparability is limited by the carve-out basis and separation transition
A9: S006 | B9: SanDisk Corporation | C9: SanDisk Reports Fiscal Fourth Quarter and Fiscal Year 2025 Financial Results | D9: 2025-08-14 | E9: E1 | F9: Company non-GAAP annual metrics | G9: https://investor.sandisk.com/news-releases/news-release-details/sandisk-reports-fiscal-fourth-quarter-and-fiscal-year-2025 | H9: Non-GAAP definitions are company-defined and are supplemental to GAAP; no like-for-like FY2023 adjusted series used
A10: S007 | B10: SanDisk Corporation | C10: SanDisk Reports Fiscal First Quarter 2026 Financial Results | D10: 2025-11-06 | E10: E1 | F10: Quarterly GAAP and non-GAAP results | G10: https://investor.sandisk.com/news-releases/news-release-details/sandisk-reports-fiscal-first-quarter-2026-financial-results | H10: Company earnings release; FY2026 Q1 has 14 weeks
A11: S008 | B11: SanDisk Corporation | C11: SanDisk Reports Fiscal First Quarter 2026 Financial Results | D11: 2025-11-06 | E11: E1 | F11: End-market revenue and free cash flow | G11: https://investor.sandisk.com/news-releases/news-release-details/sandisk-reports-fiscal-first-quarter-2026-financial-results | H11: Company-defined free cash flow excludes no separately modeled Flash Ventures adjustment in this quarter row
A12: S009 | B12: SanDisk Corporation | C12: SanDisk Reports Fiscal Second Quarter 2026 Financial Results | D12: 2026-01-29 | E12: E1 | F12: Quarterly GAAP and non-GAAP results | G12: https://investor.sandisk.com/news-releases/news-release-details/sandisk-reports-fiscal-second-quarter-2026-financial-results | H12: Company earnings release; non-GAAP figures are supplemental
A13: S010 | B13: SanDisk Corporation | C13: SanDisk Reports Fiscal Second Quarter 2026 Financial Results | D13: 2026-01-29 | E13: E1 | F13: End-market revenue and free cash flow | G13: https://investor.sandisk.com/news-releases/news-release-details/sandisk-reports-fiscal-second-quarter-2026-financial-results | H13: Quarter-only values as presented in the company release
A14: S011 | B14: SanDisk Corporation | C14: SanDisk Reports Fiscal Third Quarter 2026 Financial Results | D14: 2026-04-30 | E14: E1 | F14: Quarterly GAAP and non-GAAP results | G14: https://investor.sandisk.com/news-releases/news-release-details/sandisk-reports-fiscal-third-quarter-2026-financial-results | H14: Peak-cycle quarter; should not be assumed to represent normalized economics
... A34: S031 | B34: TrendForce | C34: AI Enterprise SSD Demand and NAND Supply Bulletin | D34: 2026-06-03 | E34: E3 | F34: Enterprise SSD supply-demand outlook | G34: https://www.trendforce.com/research/download/RP260603KA | H34: Third-party bulletin; accessible detail may be limited and no numerical SanDisk-specific forecast is provided
